{
    "version": 1,
    "series": [
        {
            "id": "M",
            "name": "MEGAシリーズ",
            "displayOrder": 1,
            "startDate": "2025-08"
        },
        {
            "id": "SV",
            "name": "スカーレット&バイオレットシリーズ",
            "displayOrder": 2,
            "startDate": "2023-01"
        },
        {
            "id": "S",
            "name": "ソード&シールドシリーズ",
            "displayOrder": 3,
            "startDate": "2019-11"
        },
        {
            "id": "SM",
            "name": "サン&ムーンシリーズ",
            "displayOrder": 4,
            "startDate": "2016-11"
        }
    ],
    "packs": [
        {
            "id": "SM1S",
            "seriesId": "SM",
            "name": "コレクション サン",
            "totalCards": 60,
            "updatedAt": "2016-12-09",
            "coverImageUrl": "https://www.pokemon-card.com/products/2016/images/sm1s.jpg",
            "jsonUrl": "https://shinya-m.github.io/pokeca-list-jpn/packs/SM/SM1S.json"
        },
        {
            "id": "SM1M",
            "seriesId": "SM",
            "name": "コレクション ムーン",
            "totalCards": 60,
            "updatedAt": "2016-12-09",
            "coverImageUrl": "https://www.pokemon-card.com/products/2016/images/sm1m.jpg",
            "jsonUrl": "https://shinya-m.github.io/pokeca-list-jpn/packs/SM/SM1M.json"
        },
        {
            "id": "SM1plus",
            "seriesId": "SM",
            "name": "サン&ムーン",
            "totalCards": 51,
            "updatedAt": "2017-01-27",
            "coverImageUrl": "https://www.pokemon-card.com/products/2017/images/sm1plus.jpg",
            "jsonUrl": "https://shinya-m.github.io/pokeca-list-jpn/packs/SM/SM1plus.json"
        },
        {
            "id": "SM2K",
            "seriesId": "SM",
            "name": "キミを待つ島々",
            "totalCards": 50,
            "updatedAt": "2017-03-17",
            "coverImageUrl": "https://www.pokemon-card.com/products/2017/images/sm2k.jpg",
            "jsonUrl": "https://shinya-m.github.io/pokeca-list-jpn/packs/SM/SM2K.json"
        },
        {
            "id": "SM2L",
            "seriesId": "SM",
            "name": "アローラの月光",
            "totalCards": 50,
            "updatedAt": "2017-03-17",
            "coverImageUrl": "https://www.pokemon-card.com/products/2017/images/sm2l.jpg",
            "jsonUrl": "https://shinya-m.github.io/pokeca-list-jpn/packs/SM/SM2L.json"
        },
        {
            "id": "SM2plus",
            "seriesId": "SM",
            "name": "新たなる試練の向こう",
            "totalCards": 49,
            "updatedAt": "2017-04-21",
            "coverImageUrl": "https://www.pokemon-card.com/products/2017/images/sm2plus.jpg",
            "jsonUrl": "https://shinya-m.github.io/pokeca-list-jpn/packs/SM/SM2plus.json"
        },
        {
            "id": "SM3H",
            "seriesId": "SM",
            "name": "闘う虹を見たか",
            "totalCards": 51,
            "updatedAt": "2017-06-16",
            "coverImageUrl": "https://www.pokemon-card.com/products/2017/images/sm3h.jpg",
            "jsonUrl": "https://shinya-m.github.io/pokeca-list-jpn/packs/SM/SM3H.json"
        },
        {
            "id": "SM3N",
            "seriesId": "SM",
            "name": "光を喰らう闇",
            "totalCards": 51,
            "updatedAt": "2017-06-16",
            "coverImageUrl": "https://www.pokemon-card.com/products/2017/images/sm3n.jpg",
            "jsonUrl": "https://shinya-m.github.io/pokeca-list-jpn/packs/SM/SM3N.json"
        },
        {
            "id": "SM3plus",
            "seriesId": "SM",
            "name": "ひかる伝説",
            "totalCards": 72,
            "updatedAt": "2017-07-15",
            "coverImageUrl": "https://www.pokemon-card.com/products/2017/images/sm3plus.jpg",
            "jsonUrl": "https://shinya-m.github.io/pokeca-list-jpn/packs/SM/SM3plus.json"
        },
        {
            "id": "SM4S",
            "seriesId": "SM",
            "name": "覚醒の勇者",
            "totalCards": 50,
            "updatedAt": "2017-09-15",
            "coverImageUrl": "https://www.pokemon-card.com/products/2017/images/sm4s.jpg",
            "jsonUrl": "https://shinya-m.github.io/pokeca-list-jpn/packs/SM/SM4S.json"
        },
        {
            "id": "SM4A",
            "seriesId": "SM",
            "name": "超次元の暴獣",
            "totalCards": 50,
            "updatedAt": "2017-09-15",
            "coverImageUrl": "https://www.pokemon-card.com/products/2017/images/sm4a.jpg",
            "jsonUrl": "https://shinya-m.github.io/pokeca-list-jpn/packs/SM/SM4A.json"
        },
        {
            "id": "SM4plus",
            "seriesId": "SM",
            "name": "GXバトルブースト",
            "totalCards": 114,
            "updatedAt": "2017-10-20",
            "coverImageUrl": "https://www.pokemon-card.com/products/2017/images/sm4plus.jpg",
            "jsonUrl": "https://shinya-m.github.io/pokeca-list-jpn/packs/SM/SM4plus.json"
        },
        {
            "id": "SM5S",
            "seriesId": "SM",
            "name": "ウルトラサン",
            "totalCards": 66,
            "updatedAt": "2017-12-08",
            "coverImageUrl": "https://www.pokemon-card.com/products/2017/images/sm5s.jpg",
            "jsonUrl": "https://shinya-m.github.io/pokeca-list-jpn/packs/SM/SM5S.json"
        },
        {
            "id": "SM5M",
            "seriesId": "SM",
            "name": "ウルトラムーン",
            "totalCards": 66,
            "updatedAt": "2017-12-08",
            "coverImageUrl": "https://www.pokemon-card.com/products/2017/images/sm5m.jpg",
            "jsonUrl": "https://shinya-m.github.io/pokeca-list-jpn/packs/SM/SM5M.json"
        },
        {
            "id": "SM5plus",
            "seriesId": "SM",
            "name": "ウルトラフォース",
            "totalCards": 50,
            "updatedAt": "2018-01-19",
            "coverImageUrl": "https://www.pokemon-card.com/products/2018/images/sm5plus.jpg",
            "jsonUrl": "https://shinya-m.github.io/pokeca-list-jpn/packs/SM/SM5plus.json"
        },
        {
            "id": "SM6",
            "seriesId": "SM",
            "name": "禁断の光",
            "totalCards": 94,
            "updatedAt": "2018-03-02",
            "coverImageUrl": "https://www.pokemon-card.com/products/2018/images/sm6.jpg",
            "jsonUrl": "https://shinya-m.github.io/pokeca-list-jpn/packs/SM/SM6.json"
        },
        {
            "id": "SM6a",
            "seriesId": "SM",
            "name": "ドラゴンストーム",
            "totalCards": 53,
            "updatedAt": "2018-04-06",
            "coverImageUrl": "https://www.pokemon-card.com/products/2018/images/sm6a.jpg",
            "jsonUrl": "https://shinya-m.github.io/pokeca-list-jpn/packs/SM/SM6a.json"
        },
        {
            "id": "SM6b",
            "seriesId": "SM",
            "name": "チャンピオンロード",
            "totalCards": 66,
            "updatedAt": "2018-05-03",
            "coverImageUrl": "https://www.pokemon-card.com/products/2018/images/sm6b.jpg",
            "jsonUrl": "https://shinya-m.github.io/pokeca-list-jpn/packs/SM/SM6b.json"
        },
        {
            "id": "SM7",
            "seriesId": "SM",
            "name": "裂空のカリスマ",
            "totalCards": 96,
            "updatedAt": "2018-06-01",
            "coverImageUrl": "https://www.pokemon-card.com/products/2018/images/sm7.jpg",
            "jsonUrl": "https://shinya-m.github.io/pokeca-list-jpn/packs/SM/SM7.json"
        },
        {
            "id": "SM7a",
            "seriesId": "SM",
            "name": "迅雷スパーク",
            "totalCards": 60,
            "updatedAt": "2018-07-06",
            "coverImageUrl": "https://www.pokemon-card.com/products/2018/images/sm7a.jpg",
            "jsonUrl": "https://shinya-m.github.io/pokeca-list-jpn/packs/SM/SM7a.json"
        },
        {
            "id": "SM7b",
            "seriesId": "SM",
            "name": "フェアリーライズ",
            "totalCards": 50,
            "updatedAt": "2018-08-03",
            "coverImageUrl": "https://www.pokemon-card.com/products/2018/images/sm7b.jpg",
            "jsonUrl": "https://shinya-m.github.io/pokeca-list-jpn/packs/SM/SM7b.json"
        },
        {
            "id": "SM8",
            "seriesId": "SM",
            "name": "超爆インパクト",
            "totalCards": 95,
            "updatedAt": "2018-09-07",
            "coverImageUrl": "https://www.pokemon-card.com/products/2018/images/sm8.jpg",
            "jsonUrl": "https://shinya-m.github.io/pokeca-list-jpn/packs/SM/SM8.json"
        },
        {
            "id": "SM8a",
            "seriesId": "SM",
            "name": "ダークオーダー",
            "totalCards": 52,
            "updatedAt": "2018-10-05",
            "coverImageUrl": "https://www.pokemon-card.com/products/2018/images/sm8a.jpg",
            "jsonUrl": "https://shinya-m.github.io/pokeca-list-jpn/packs/SM/SM8a.json"
        },
        {
            "id": "SM8b",
            "seriesId": "SM",
            "name": "GXウルトラシャイニー",
            "totalCards": 150,
            "updatedAt": "2018-11-02",
            "coverImageUrl": "https://www.pokemon-card.com/products/2018/images/sm8b.jpg",
            "jsonUrl": "https://shinya-m.github.io/pokeca-list-jpn/packs/SM/SM8b.json"
        },
        {
            "id": "SM9",
            "seriesId": "SM",
            "name": "タッグボルト",
            "totalCards": 95,
            "updatedAt": "2018-12-07",
            "coverImageUrl": "https://www.pokemon-card.com/products/2018/images/sm9.jpg",
            "jsonUrl": "https://shinya-m.github.io/pokeca-list-jpn/packs/SM/SM9.json"
        },
        {
            "id": "SM9a",
            "seriesId": "SM",
            "name": "ナイトユニゾン",
            "totalCards": 55,
            "updatedAt": "2019-01-11",
            "coverImageUrl": "https://www.pokemon-card.com/products/2019/images/sm9a.jpg",
            "jsonUrl": "https://shinya-m.github.io/pokeca-list-jpn/packs/SM/SM9a.json"
        },
        {
            "id": "SM9b",
            "seriesId": "SM",
            "name": "フルメタルウォール",
            "totalCards": 54,
            "updatedAt": "2019-02-01",
            "coverImageUrl": "https://www.pokemon-card.com/products/2019/images/sm9b.jpg",
            "jsonUrl": "https://shinya-m.github.io/pokeca-list-jpn/packs/SM/SM9b.json"
        },
        {
            "id": "SM10",
            "seriesId": "SM",
            "name": "ダブルブレイズ",
            "totalCards": 95,
            "updatedAt": "2019-03-01",
            "coverImageUrl": "https://www.pokemon-card.com/products/2019/images/sm10.jpg",
            "jsonUrl": "https://shinya-m.github.io/pokeca-list-jpn/packs/SM/SM10.json"
        },
        {
            "id": "SM10a",
            "seriesId": "SM",
            "name": "ジージーエンド",
            "totalCards": 54,
            "updatedAt": "2019-04-05",
            "coverImageUrl": "https://www.pokemon-card.com/products/2019/images/sm10a.jpg",
            "jsonUrl": "https://shinya-m.github.io/pokeca-list-jpn/packs/SM/SM10a.json"
        },
        {
            "id": "SM10b",
            "seriesId": "SM",
            "name": "スカイレジェンド",
            "totalCards": 54,
            "updatedAt": "2019-04-26",
            "coverImageUrl": "https://www.pokemon-card.com/products/2019/images/sm10b.jpg",
            "jsonUrl": "https://shinya-m.github.io/pokeca-list-jpn/packs/SM/SM10b.json"
        },
        {
            "id": "SM11",
            "seriesId": "SM",
            "name": "ミラクルツイン",
            "totalCards": 94,
            "updatedAt": "2019-05-31",
            "coverImageUrl": "https://www.pokemon-card.com/products/2019/images/sm11.jpg",
            "jsonUrl": "https://shinya-m.github.io/pokeca-list-jpn/packs/SM/SM11.json"
        },
        {
            "id": "SM11a",
            "seriesId": "SM",
            "name": "リミックスバウト",
            "totalCards": 64,
            "updatedAt": "2019-07-05",
            "coverImageUrl": "https://www.pokemon-card.com/products/2019/images/sm11a.jpg",
            "jsonUrl": "https://shinya-m.github.io/pokeca-list-jpn/packs/SM/SM11a.json"
        },
        {
            "id": "SM11b",
            "seriesId": "SM",
            "name": "ドリームリーグ",
            "totalCards": 49,
            "updatedAt": "2019-08-02",
            "coverImageUrl": "https://www.pokemon-card.com/products/2019/images/sm11b.jpg",
            "jsonUrl": "https://shinya-m.github.io/pokeca-list-jpn/packs/SM/SM11b.json"
        },
        {
            "id": "SM12",
            "seriesId": "SM",
            "name": "オルタージェネシス",
            "totalCards": 95,
            "updatedAt": "2019-09-06",
            "coverImageUrl": "https://www.pokemon-card.com/products/2019/images/sm12.jpg",
            "jsonUrl": "https://shinya-m.github.io/pokeca-list-jpn/packs/SM/SM12.json"
        },
        {
            "id": "SM12a",
            "seriesId": "SM",
            "name": "タッグオールスターズ",
            "totalCards": 173,
            "updatedAt": "2019-10-04",
            "coverImageUrl": "https://www.pokemon-card.com/products/2019/images/sm12a.jpg",
            "jsonUrl": "https://shinya-m.github.io/pokeca-list-jpn/packs/SM/SM12a.json"
        },
        {
            "id": "S1W",
            "seriesId": "S",
            "name": "ソード",
            "totalCards": 60,
            "updatedAt": "2019-12-06",
            "coverImageUrl": "https://www.pokemon-card.com/products/2019/images/1401_S1w_pillow_img.jpg",
            "jsonUrl": "https://shinya-m.github.io/pokeca-list-jpn/packs/S/S1W.json"
        },
        {
            "id": "S1H",
            "seriesId": "S",
            "name": "シールド",
            "totalCards": 60,
            "updatedAt": "2019-12-06",
            "coverImageUrl": "https://www.pokemon-card.com/products/2019/images/1402_S1h_pillow_img.jpg",
            "jsonUrl": "https://shinya-m.github.io/pokeca-list-jpn/packs/S/S1H.json"
        },
        {
            "id": "S1a",
            "seriesId": "S",
            "name": "VMAXライジング",
            "totalCards": 70,
            "updatedAt": "2020-02-07",
            "coverImageUrl": "https://www.pokemon-card.com/products/2020/images/1405_S1a_pillow_img.png",
            "jsonUrl": "https://shinya-m.github.io/pokeca-list-jpn/packs/S/S1a.json"
        },
        {
            "id": "S2",
            "seriesId": "S",
            "name": "反逆クラッシュ",
            "totalCards": 96,
            "updatedAt": "2020-03-06",
            "coverImageUrl": "https://www.pokemon-card.com/products/2020/images/1406_S2_pillow_img.jpg",
            "jsonUrl": "https://shinya-m.github.io/pokeca-list-jpn/packs/S/S2.json"
        },
        {
            "id": "S2a",
            "seriesId": "S",
            "name": "爆炎ウォーカー",
            "totalCards": 70,
            "updatedAt": "2020-04-24",
            "coverImageUrl": "https://www.pokemon-card.com/products/2020/images/1409_S2a_pillow_img.jpg",
            "jsonUrl": "https://shinya-m.github.io/pokeca-list-jpn/packs/S/S2a.json"
        },
        {
            "id": "S3",
            "seriesId": "S",
            "name": "ムゲンゾーン",
            "totalCards": 100,
            "updatedAt": "2020-06-05",
            "coverImageUrl": "https://www.pokemon-card.com/products/2020/images/1410_S3_pillow_img-.png",
            "jsonUrl": "https://shinya-m.github.io/pokeca-list-jpn/packs/S/S3.json"
        },
        {
            "id": "S3a",
            "seriesId": "S",
            "name": "伝説の鼓動",
            "totalCards": 76,
            "updatedAt": "2020-07-10",
            "coverImageUrl": "https://www.pokemon-card.com/products/2020/images/1411_S3a_pillow_img.jpg",
            "jsonUrl": "https://shinya-m.github.io/pokeca-list-jpn/packs/S/S3a.json"
        },
        {
            "id": "S4",
            "seriesId": "S",
            "name": "仰天のボルテッカー",
            "totalCards": 100,
            "updatedAt": "2020-09-18",
            "coverImageUrl": "https://www.pokemon-card.com/products/2020/images/S4_PKG.jpg",
            "jsonUrl": "https://shinya-m.github.io/pokeca-list-jpn/packs/S/S4.json"
        },
        {
            "id": "S4a",
            "seriesId": "S",
            "name": "シャイニースターV",
            "totalCards": 190,
            "updatedAt": "2020-11-20",
            "coverImageUrl": "https://www.pokemon-card.com/products/2020/images/s4a.jpg",
            "jsonUrl": "https://shinya-m.github.io/pokeca-list-jpn/packs/S/S4a.json"
        },
        {
            "id": "S5I",
            "seriesId": "S",
            "name": "一撃マスター",
            "totalCards": 70,
            "updatedAt": "2021-01-22",
            "coverImageUrl": "https://www.pokemon-card.com/products/2020/images/ichigeki.jpg",
            "jsonUrl": "https://shinya-m.github.io/pokeca-list-jpn/packs/S/S5I.json"
        },
        {
            "id": "S5R",
            "seriesId": "S",
            "name": "連撃マスター",
            "totalCards": 70,
            "updatedAt": "2021-01-22",
            "coverImageUrl": "https://www.pokemon-card.com/products/2020/images/rengeki.jpg",
            "jsonUrl": "https://shinya-m.github.io/pokeca-list-jpn/packs/S/S5R.json"
        },
        {
            "id": "S5a",
            "seriesId": "S",
            "name": "双璧のファイター",
            "totalCards": 70,
            "updatedAt": "2021-03-19",
            "coverImageUrl": "https://www.pokemon-card.com/products/2021/images/S5aPKG.jpg",
            "jsonUrl": "https://shinya-m.github.io/pokeca-list-jpn/packs/S/S5a.json"
        },
        {
            "id": "S6H",
            "seriesId": "S",
            "name": "白銀のランス",
            "totalCards": 70,
            "updatedAt": "2021-04-23",
            "coverImageUrl": "https://www.pokemon-card.com/products/2021/images/S6H.jpg",
            "jsonUrl": "https://shinya-m.github.io/pokeca-list-jpn/packs/S/S6H.json"
        },
        {
            "id": "S6K",
            "seriesId": "S",
            "name": "漆黒のガイスト",
            "totalCards": 70,
            "updatedAt": "2021-04-23",
            "coverImageUrl": "https://www.pokemon-card.com/products/2021/images/S6K.jpg",
            "jsonUrl": "https://shinya-m.github.io/pokeca-list-jpn/packs/S/S6K.json"
        },
        {
            "id": "S6a",
            "seriesId": "S",
            "name": "イーブイヒーローズ",
            "totalCards": 69,
            "updatedAt": "2021-05-28",
            "coverImageUrl": "https://www.pokemon-card.com/products/2021/images/S6a_pillow.jpg",
            "jsonUrl": "https://shinya-m.github.io/pokeca-list-jpn/packs/S/S6a.json"
        },
        {
            "id": "S7D",
            "seriesId": "S",
            "name": "摩天パーフェクト",
            "totalCards": 67,
            "updatedAt": "2021-07-09",
            "coverImageUrl": "https://www.pokemon-card.com/products/2021/images/S7D.jpg",
            "jsonUrl": "https://shinya-m.github.io/pokeca-list-jpn/packs/S/S7D.json"
        },
        {
            "id": "S7R",
            "seriesId": "S",
            "name": "蒼空ストリーム",
            "totalCards": 67,
            "updatedAt": "2021-07-09",
            "coverImageUrl": "https://www.pokemon-card.com/products/2021/images/S7R.jpg",
            "jsonUrl": "https://shinya-m.github.io/pokeca-list-jpn/packs/S/S7R.json"
        },
        {
            "id": "S8",
            "seriesId": "S",
            "name": "フュージョンアーツ",
            "totalCards": 100,
            "updatedAt": "2021-09-24",
            "coverImageUrl": "https://www.pokemon-card.com/products/2021/images/S8.jpg",
            "jsonUrl": "https://shinya-m.github.io/pokeca-list-jpn/packs/S/S8.json"
        },
        {
            "id": "S8a",
            "seriesId": "S",
            "name": "25th ANNIVERSARY COLLECTION",
            "totalCards": 28,
            "updatedAt": "2021-10-22",
            "coverImageUrl": "https://www.pokemon-card.com/products/2021/images/S8a_pillow.jpg",
            "jsonUrl": "https://shinya-m.github.io/pokeca-list-jpn/packs/S/S8a.json"
        },
        {
            "id": "S8b",
            "seriesId": "S",
            "name": "VMAXクライマックス",
            "totalCards": 184,
            "updatedAt": "2021-12-03",
            "coverImageUrl": "https://www.pokemon-card.com/products/2021/images/S8b_PKG.jpg",
            "jsonUrl": "https://shinya-m.github.io/pokeca-list-jpn/packs/S/S8b.json"
        },
        {
            "id": "S9",
            "seriesId": "S",
            "name": "スターバース",
            "totalCards": 100,
            "updatedAt": "2022-01-14",
            "coverImageUrl": "https://www.pokemon-card.com/products/2021/images/S9_PKG.jpg",
            "jsonUrl": "https://shinya-m.github.io/pokeca-list-jpn/packs/S/S9.json"
        },
        {
            "id": "S9a",
            "seriesId": "S",
            "name": "バトルリージョン",
            "totalCards": 67,
            "updatedAt": "2022-02-25",
            "coverImageUrl": "https://www.pokemon-card.com/products/2022/images/S9a_PKG.jpg",
            "jsonUrl": "https://shinya-m.github.io/pokeca-list-jpn/packs/S/S9a.json"
        },
        {
            "id": "S10D",
            "seriesId": "S",
            "name": "タイムゲイザー",
            "totalCards": 67,
            "updatedAt": "2022-04-08",
            "coverImageUrl": "https://www.pokemon-card.com/products/2022/images/s10d.jpg",
            "jsonUrl": "https://shinya-m.github.io/pokeca-list-jpn/packs/S/S10D.json"
        },
        {
            "id": "S10P",
            "seriesId": "S",
            "name": "スペースジャグラー",
            "totalCards": 67,
            "updatedAt": "2022-04-08",
            "coverImageUrl": "https://www.pokemon-card.com/products/2022/images/s10p.jpg",
            "jsonUrl": "https://shinya-m.github.io/pokeca-list-jpn/packs/S/S10P.json"
        },
        {
            "id": "S10a",
            "seriesId": "S",
            "name": "ダークファンタズマ",
            "totalCards": 71,
            "updatedAt": "2022-05-13",
            "coverImageUrl": "https://www.pokemon-card.com/products/2022/images/s10a.jpg",
            "jsonUrl": "https://shinya-m.github.io/pokeca-list-jpn/packs/S/S10a.json"
        },
        {
            "id": "S10b",
            "seriesId": "S",
            "name": "Pokémon GO",
            "totalCards": 71,
            "updatedAt": "2022-06-17",
            "coverImageUrl": "https://www.pokemon-card.com/products/2022/images/S10b.jpg",
            "jsonUrl": "https://shinya-m.github.io/pokeca-list-jpn/packs/S/S10b.json"
        },
        {
            "id": "S11",
            "seriesId": "S",
            "name": "ロストアビス",
            "totalCards": 100,
            "updatedAt": "2022-07-15",
            "coverImageUrl": "https://www.pokemon-card.com/products/2022/images/s11_pillow.jpg",
            "jsonUrl": "https://shinya-m.github.io/pokeca-list-jpn/packs/S/S11.json"
        },
        {
            "id": "S11a",
            "seriesId": "S",
            "name": "白熱のアルカナ",
            "totalCards": 68,
            "updatedAt": "2022-09-02",
            "coverImageUrl": "https://www.pokemon-card.com/products/2022/images/S11a_pillow.jpg",
            "jsonUrl": "https://shinya-m.github.io/pokeca-list-jpn/packs/S/S11a.json"
        },
        {
            "id": "S12",
            "seriesId": "S",
            "name": "パラダイムトリガー",
            "totalCards": 98,
            "updatedAt": "2022-10-21",
            "coverImageUrl": "https://www.pokemon-card.com/products/2022/images/s12.jpg",
            "jsonUrl": "https://shinya-m.github.io/pokeca-list-jpn/packs/S/S12.json"
        },
        {
            "id": "S12a",
            "seriesId": "S",
            "name": "VSTARユニバース",
            "totalCards": 172,
            "updatedAt": "2022-12-02",
            "coverImageUrl": "https://www.pokemon-card.com/products/2022/images/s12a.jpg",
            "jsonUrl": "https://shinya-m.github.io/pokeca-list-jpn/packs/S/S12a.json"
        },
        {
            "id": "SV1S",
            "seriesId": "SV",
            "name": "スカーレットex",
            "totalCards": 78,
            "updatedAt": "2023-01-20",
            "coverImageUrl": "https://www.pokemon-card.com/products/2022/images/sv1s_pillow.jpg",
            "jsonUrl": "https://shinya-m.github.io/pokeca-list-jpn/packs/SV/SV1S.json"
        },
        {
            "id": "SV1V",
            "seriesId": "SV",
            "name": "バイオレットex",
            "totalCards": 78,
            "updatedAt": "2023-01-20",
            "coverImageUrl": "https://www.pokemon-card.com/products/2022/images/sv1v_pillow.jpg",
            "jsonUrl": "https://shinya-m.github.io/pokeca-list-jpn/packs/SV/SV1V.json"
        },
        {
            "id": "SV1a",
            "seriesId": "SV",
            "name": "トリプレットビート",
            "totalCards": 73,
            "updatedAt": "2023-03-10",
            "coverImageUrl": "https://www.pokemon-card.com/products/2023/images/SV1a_PKG.jpg",
            "jsonUrl": "https://shinya-m.github.io/pokeca-list-jpn/packs/SV/SV1a.json"
        },
        {
            "id": "SV2P",
            "seriesId": "SV",
            "name": "スノーハザード",
            "totalCards": 71,
            "updatedAt": "2023-04-14",
            "coverImageUrl": "https://www.pokemon-card.com/products/2023/images/sv2p.jpg",
            "jsonUrl": "https://shinya-m.github.io/pokeca-list-jpn/packs/SV/SV2P.json"
        },
        {
            "id": "SV2D",
            "seriesId": "SV",
            "name": "クレイバースト",
            "totalCards": 71,
            "updatedAt": "2023-04-14",
            "coverImageUrl": "https://www.pokemon-card.com/products/2023/images/sv2d.jpg",
            "jsonUrl": "https://shinya-m.github.io/pokeca-list-jpn/packs/SV/SV2D.json"
        },
        {
            "id": "SV2a",
            "seriesId": "SV",
            "name": "ポケモンカード151",
            "totalCards": 165,
            "updatedAt": "2023-06-16",
            "coverImageUrl": "https://www.pokemon-card.com/products/2023/images/sv2a.jpg",
            "jsonUrl": "https://shinya-m.github.io/pokeca-list-jpn/packs/SV/SV2a.json"
        },
        {
            "id": "SV3",
            "seriesId": "SV",
            "name": "黒炎の支配者",
            "totalCards": 108,
            "updatedAt": "2023-07-28",
            "coverImageUrl": "https://www.pokemon-card.com/products/2023/images/sv3.jpg",
            "jsonUrl": "https://shinya-m.github.io/pokeca-list-jpn/packs/SV/SV3.json"
        },
        {
            "id": "SV3a",
            "seriesId": "SV",
            "name": "レイジングサーフ",
            "totalCards": 62,
            "updatedAt": "2023-09-22",
            "coverImageUrl": "https://www.pokemon-card.com/products/2023/images/sv3_pkg_2.jpg",
            "jsonUrl": "https://shinya-m.github.io/pokeca-list-jpn/packs/SV/SV3a.json"
        },
        {
            "id": "SV4K",
            "seriesId": "SV",
            "name": "古代の咆哮",
            "totalCards": 66,
            "updatedAt": "2023-10-27",
            "coverImageUrl": "https://www.pokemon-card.com/products/2023/images/sv4k_pkg.jpg",
            "jsonUrl": "https://shinya-m.github.io/pokeca-list-jpn/packs/SV/SV4K.json"
        },
        {
            "id": "SV4M",
            "seriesId": "SV",
            "name": "未来の一閃",
            "totalCards": 66,
            "updatedAt": "2023-10-27",
            "coverImageUrl": "https://www.pokemon-card.com/products/2023/images/sv4m_pkg.jpg",
            "jsonUrl": "https://shinya-m.github.io/pokeca-list-jpn/packs/SV/SV4M.json"
        },
        {
            "id": "SV4a",
            "seriesId": "SV",
            "name": "シャイニートレジャーex",
            "totalCards": 190,
            "updatedAt": "2023-12-01",
            "coverImageUrl": "https://www.pokemon-card.com/products/2024/images/8e09f54354fc14218aadc0b0e85f86f301f57d22.jpg",
            "jsonUrl": "https://shinya-m.github.io/pokeca-list-jpn/packs/SV/SV4a.json"
        },
        {
            "id": "SV5K",
            "seriesId": "SV",
            "name": "ワイルドフォース",
            "totalCards": 71,
            "updatedAt": "2024-01-26",
            "coverImageUrl": "https://www.pokemon-card.com/products/2023/images/SV5_21.jpg",
            "jsonUrl": "https://shinya-m.github.io/pokeca-list-jpn/packs/SV/SV5K.json"
        },
        {
            "id": "SV5M",
            "seriesId": "SV",
            "name": "サイバージャッジ",
            "totalCards": 71,
            "updatedAt": "2024-01-26",
            "coverImageUrl": "https://www.pokemon-card.com/products/2023/images/SV5_20.jpg",
            "jsonUrl": "https://shinya-m.github.io/pokeca-list-jpn/packs/SV/SV5M.json"
        },
        {
            "id": "SV5a",
            "seriesId": "SV",
            "name": "クリムゾンヘイズ",
            "totalCards": 66,
            "updatedAt": "2024-03-22",
            "coverImageUrl": "https://www.pokemon-card.com/products/2024/images/sv5a_PKG.jpg",
            "jsonUrl": "https://shinya-m.github.io/pokeca-list-jpn/packs/SV/SV5a.json"
        },
        {
            "id": "SV6",
            "seriesId": "SV",
            "name": "変幻の仮面",
            "totalCards": 101,
            "updatedAt": "2024-04-26",
            "coverImageUrl": "https://www.pokemon-card.com/products/2024/images/SV6.jpg",
            "jsonUrl": "https://shinya-m.github.io/pokeca-list-jpn/packs/SV/SV6.json"
        },
        {
            "id": "SV6a",
            "seriesId": "SV",
            "name": "ナイトワンダラー",
            "totalCards": 64,
            "updatedAt": "2024-06-07",
            "coverImageUrl": "https://www.pokemon-card.com/products/2024/images/sv6a.jpg",
            "jsonUrl": "https://shinya-m.github.io/pokeca-list-jpn/packs/SV/SV6a.json"
        },
        {
            "id": "SV7",
            "seriesId": "SV",
            "name": "ステラミラクル",
            "totalCards": 102,
            "updatedAt": "2024-07-19",
            "coverImageUrl": "https://www.pokemon-card.com/products/2024/images/pakku_suteramirakuru.jpg",
            "jsonUrl": "https://shinya-m.github.io/pokeca-list-jpn/packs/SV/SV7.json"
        },
        {
            "id": "SV7a",
            "seriesId": "SV",
            "name": "楽園ドラゴーナ",
            "totalCards": 64,
            "updatedAt": "2024-09-13",
            "coverImageUrl": "https://www.pokemon-card.com/products/2024/images/sv7a_pillow_thumbnail.jpg",
            "jsonUrl": "https://shinya-m.github.io/pokeca-list-jpn/packs/SV/SV7a.json"
        },
        {
            "id": "SV8",
            "seriesId": "SV",
            "name": "超電ブレイカー",
            "totalCards": 106,
            "updatedAt": "2024-10-18",
            "coverImageUrl": "https://www.pokemon-card.com/products/2024/images/pakku_choudenbureika.jpg",
            "jsonUrl": "https://shinya-m.github.io/pokeca-list-jpn/packs/SV/SV8.json"
        },
        {
            "id": "SV8a",
            "seriesId": "SV",
            "name": "テラスタルフェスex",
            "totalCards": 187,
            "updatedAt": "2024-12-06",
            "coverImageUrl": "https://www.pokemon-card.com/products/2024/images/sv8a.jpg",
            "jsonUrl": "https://shinya-m.github.io/pokeca-list-jpn/packs/SV/SV8a.json"
        },
        {
            "id": "SV9",
            "seriesId": "SV",
            "name": "バトルパートナーズ",
            "totalCards": 132,
            "updatedAt": "2025-01-24",
            "coverImageUrl": "https://www.pokemon-card.com/products/2024/images/sv9.jpg",
            "jsonUrl": "https://shinya-m.github.io/pokeca-list-jpn/packs/SV/SV9.json"
        },
        {
            "id": "SV9a",
            "seriesId": "SV",
            "name": "熱風のアリーナ",
            "totalCards": 92,
            "updatedAt": "2025-03-14",
            "coverImageUrl": "https://www.pokemon-card.com/products/2025/images/sv9a.jpg",
            "jsonUrl": "https://shinya-m.github.io/pokeca-list-jpn/packs/SV/SV9a.json"
        },
        {
            "id": "SV10",
            "seriesId": "SV",
            "name": "ロケット団の栄光",
            "totalCards": 132,
            "updatedAt": "2025-04-18",
            "coverImageUrl": "https://www.pokemon-card.com/products/2025/images/sv10.jpg",
            "jsonUrl": "https://shinya-m.github.io/pokeca-list-jpn/packs/SV/SV10.json"
        },
        {
            "id": "SV11W",
            "seriesId": "SV",
            "name": "ホワイトフレア",
            "totalCards": 174,
            "updatedAt": "2025-06-06",
            "coverImageUrl": "https://www.pokemon-card.com/products/2025/images/sv11w.jpg",
            "jsonUrl": "https://shinya-m.github.io/pokeca-list-jpn/packs/SV/SV11W.json"
        },
        {
            "id": "SV11B",
            "seriesId": "SV",
            "name": "ブラックボルト",
            "totalCards": 174,
            "updatedAt": "2025-06-06",
            "coverImageUrl": "https://www.pokemon-card.com/products/2025/images/sv11b.jpg",
            "jsonUrl": "https://shinya-m.github.io/pokeca-list-jpn/packs/SV/SV11B.json"
        },
        {
            "id": "M1S",
            "seriesId": "M",
            "name": "メガシンフォニア",
            "totalCards": 92,
            "updatedAt": "2025-08-01",
            "coverImageUrl": "https://www.pokemon-card.com/products/2025/images/M1S.jpg",
            "jsonUrl": "https://shinya-m.github.io/pokeca-list-jpn/packs/M/M1S.json"
        },
        {
            "id": "M1L",
            "seriesId": "M",
            "name": "メガブレイブ",
            "totalCards": 92,
            "updatedAt": "2025-08-01",
            "coverImageUrl": "https://www.pokemon-card.com/products/2025/images/M1L.jpg",
            "jsonUrl": "https://shinya-m.github.io/pokeca-list-jpn/packs/M/M1L.json"
        },
        {
            "id": "M2",
            "seriesId": "M",
            "name": "インフェルノX",
            "totalCards": 116,
            "updatedAt": "2025-09-26",
            "coverImageUrl": "https://www.pokemon-card.com/products/2025/images/M2.jpg",
            "jsonUrl": "https://shinya-m.github.io/pokeca-list-jpn/packs/M/M2.json"
        },
        {
            "id": "M2a",
            "seriesId": "M",
            "name": "MEGAドリームex",
            "totalCards": 250,
            "updatedAt": "2025-11-28",
            "coverImageUrl": "https://www.pokemon-card.com/products/2025/images/m2a.jpg",
            "jsonUrl": "https://shinya-m.github.io/pokeca-list-jpn/packs/M/M2a.json"
        },
        {
            "id": "M3",
            "seriesId": "M",
            "name": "ムニキスゼロ",
            "totalCards": 117,
            "updatedAt": "2026-01-23",
            "coverImageUrl": "https://www.pokemon-card.com/products/2025/images/m3.jpg",
            "jsonUrl": "https://shinya-m.github.io/pokeca-list-jpn/packs/M/M3.json"
        }
    ]
}