{
    "packId": "S7D",
    "cards": [
        {
            "id": "S7D-001",
            "number": "001/067",
            "name": "スイクンV",
            "rarity": "RR",
            "imageUrl": "https://www.pokemon-card.com/assets/images/card_images/large/S7D/039670_P_SUIKUNV.jpg"
        },
        {
            "id": "S7D-002",
            "number": "002/067",
            "name": "ハスボー",
            "rarity": "C",
            "imageUrl": "https://www.pokemon-card.com/assets/images/card_images/large/S7D/039671_P_HASUBO.jpg"
        },
        {
            "id": "S7D-003",
            "number": "003/067",
            "name": "ハスブレロ",
            "rarity": "C",
            "imageUrl": "https://www.pokemon-card.com/assets/images/card_images/large/S7D/039672_P_HASUBURERO.jpg"
        },
        {
            "id": "S7D-004",
            "number": "004/067",
            "name": "ルンパッパ",
            "rarity": "R",
            "imageUrl": "https://www.pokemon-card.com/assets/images/card_images/large/S7D/039673_P_RUNPAPPA.jpg"
        },
        {
            "id": "S7D-005",
            "number": "005/067",
            "name": "ヒヤップ",
            "rarity": "C",
            "imageUrl": "https://www.pokemon-card.com/assets/images/card_images/large/S7D/039674_P_HIYAPPU.jpg"
        },
        {
            "id": "S7D-006",
            "number": "006/067",
            "name": "ヒヤッキー",
            "rarity": "C",
            "imageUrl": "https://www.pokemon-card.com/assets/images/card_images/large/S7D/039675_P_HIYAKKI.jpg"
        },
        {
            "id": "S7D-007",
            "number": "007/067",
            "name": "ウデッポウ",
            "rarity": "C",
            "imageUrl": "https://www.pokemon-card.com/assets/images/card_images/large/S7D/039676_P_UDEPPOU.jpg"
        },
        {
            "id": "S7D-008",
            "number": "008/067",
            "name": "ブロスター",
            "rarity": "C",
            "imageUrl": "https://www.pokemon-card.com/assets/images/card_images/large/S7D/039677_P_BUROSUTA.jpg"
        },
        {
            "id": "S7D-009",
            "number": "009/067",
            "name": "コオリッポ",
            "rarity": "U",
            "imageUrl": "https://www.pokemon-card.com/assets/images/card_images/large/S7D/039678_P_KOORIPPO.jpg"
        },
        {
            "id": "S7D-010",
            "number": "010/067",
            "name": "プリン",
            "rarity": "C",
            "imageUrl": "https://www.pokemon-card.com/assets/images/card_images/large/S7D/039679_P_PURIN.jpg"
        },
        {
            "id": "S7D-011",
            "number": "011/067",
            "name": "プクリン",
            "rarity": "C",
            "imageUrl": "https://www.pokemon-card.com/assets/images/card_images/large/S7D/039680_P_PUKURIN.jpg"
        },
        {
            "id": "S7D-012",
            "number": "012/067",
            "name": "ガラル フリーザー",
            "rarity": "R",
            "imageUrl": "https://www.pokemon-card.com/assets/images/card_images/large/S7D/039681_P_GARARUFURIZA.jpg"
        },
        {
            "id": "S7D-013",
            "number": "013/067",
            "name": "ソーナンス",
            "rarity": "U",
            "imageUrl": "https://www.pokemon-card.com/assets/images/card_images/large/S7D/039682_P_SONANSU.jpg"
        },
        {
            "id": "S7D-014",
            "number": "014/067",
            "name": "シンボラー",
            "rarity": "C",
            "imageUrl": "https://www.pokemon-card.com/assets/images/card_images/large/S7D/039683_P_SHINBORA.jpg"
        },
        {
            "id": "S7D-015",
            "number": "015/067",
            "name": "ゴルーグV",
            "rarity": "RR",
            "imageUrl": "https://www.pokemon-card.com/assets/images/card_images/large/S7D/039684_P_GORUGUV.jpg"
        },
        {
            "id": "S7D-016",
            "number": "016/067",
            "name": "バケッチャ",
            "rarity": "C",
            "imageUrl": "https://www.pokemon-card.com/assets/images/card_images/large/S7D/039685_P_BAKECCHA.jpg"
        },
        {
            "id": "S7D-017",
            "number": "017/067",
            "name": "パンプジン",
            "rarity": "U",
            "imageUrl": "https://www.pokemon-card.com/assets/images/card_images/large/S7D/039686_P_PANPUJIN.jpg"
        },
        {
            "id": "S7D-018",
            "number": "018/067",
            "name": "エビワラー",
            "rarity": "C",
            "imageUrl": "https://www.pokemon-card.com/assets/images/card_images/large/S7D/039687_P_EBIWARA.jpg"
        },
        {
            "id": "S7D-019",
            "number": "019/067",
            "name": "ガラル サンダー",
            "rarity": "R",
            "imageUrl": "https://www.pokemon-card.com/assets/images/card_images/large/S7D/039688_P_GARARUSANDA.jpg"
        },
        {
            "id": "S7D-020",
            "number": "020/067",
            "name": "グライガー",
            "rarity": "C",
            "imageUrl": "https://www.pokemon-card.com/assets/images/card_images/large/S7D/039689_P_GURAIGA.jpg"
        },
        {
            "id": "S7D-021",
            "number": "021/067",
            "name": "グライオン",
            "rarity": "C",
            "imageUrl": "https://www.pokemon-card.com/assets/images/card_images/large/S7D/039690_P_GURAION.jpg"
        },
        {
            "id": "S7D-022",
            "number": "022/067",
            "name": "マクノシタ",
            "rarity": "C",
            "imageUrl": "https://www.pokemon-card.com/assets/images/card_images/large/S7D/039691_P_MAKUNOSHITA.jpg"
        },
        {
            "id": "S7D-023",
            "number": "023/067",
            "name": "ハリテヤマ",
            "rarity": "U",
            "imageUrl": "https://www.pokemon-card.com/assets/images/card_images/large/S7D/039692_P_HARITEYAMA.jpg"
        },
        {
            "id": "S7D-024",
            "number": "024/067",
            "name": "ルガルガンV",
            "rarity": "RR",
            "imageUrl": "https://www.pokemon-card.com/assets/images/card_images/large/S7D/039693_P_RUGARUGANV.jpg"
        },
        {
            "id": "S7D-025",
            "number": "025/067",
            "name": "ルガルガンVMAX",
            "rarity": "-",
            "imageUrl": "https://www.pokemon-card.com/assets/images/card_images/large/S7D/039694_P_RUGARUGANVMAX.jpg"
        },
        {
            "id": "S7D-026",
            "number": "026/067",
            "name": "ガラル ファイヤー",
            "rarity": "R",
            "imageUrl": "https://www.pokemon-card.com/assets/images/card_images/large/S7D/039695_P_GARARUFAIYA.jpg"
        },
        {
            "id": "S7D-027",
            "number": "027/067",
            "name": "アブソル",
            "rarity": "U",
            "imageUrl": "https://www.pokemon-card.com/assets/images/card_images/large/S7D/039696_P_ABUSORU.jpg"
        },
        {
            "id": "S7D-028",
            "number": "028/067",
            "name": "グレッグル",
            "rarity": "C",
            "imageUrl": "https://www.pokemon-card.com/assets/images/card_images/large/S7D/039697_P_GUREGGURU.jpg"
        },
        {
            "id": "S7D-029",
            "number": "029/067",
            "name": "ドクロッグ",
            "rarity": "U",
            "imageUrl": "https://www.pokemon-card.com/assets/images/card_images/large/S7D/039698_P_DOKUROGGU.jpg"
        },
        {
            "id": "S7D-030",
            "number": "030/067",
            "name": "ダストダスV",
            "rarity": "RR",
            "imageUrl": "https://www.pokemon-card.com/assets/images/card_images/large/S7D/039699_P_DASUTODASUV.jpg"
        },
        {
            "id": "S7D-031",
            "number": "031/067",
            "name": "ダストダスVMAX",
            "rarity": "-",
            "imageUrl": "https://www.pokemon-card.com/assets/images/card_images/large/S7D/039700_P_DASUTODASUVMAX.jpg"
        },
        {
            "id": "S7D-032",
            "number": "032/067",
            "name": "クスネ",
            "rarity": "C",
            "imageUrl": "https://www.pokemon-card.com/assets/images/card_images/large/S7D/039701_P_KUSUNE.jpg"
        },
        {
            "id": "S7D-033",
            "number": "033/067",
            "name": "フォクスライ",
            "rarity": "U",
            "imageUrl": "https://www.pokemon-card.com/assets/images/card_images/large/S7D/039702_P_FOKUSURAI.jpg"
        },
        {
            "id": "S7D-034",
            "number": "034/067",
            "name": "ガラル ニャース",
            "rarity": "C",
            "imageUrl": "https://www.pokemon-card.com/assets/images/card_images/large/S7D/039703_P_GARARUNYASU.jpg"
        },
        {
            "id": "S7D-035",
            "number": "035/067",
            "name": "ガラル ニャイキング",
            "rarity": "U",
            "imageUrl": "https://www.pokemon-card.com/assets/images/card_images/large/S7D/039704_P_GARARUNYAIKINGU.jpg"
        },
        {
            "id": "S7D-036",
            "number": "036/067",
            "name": "エアームド",
            "rarity": "C",
            "imageUrl": "https://www.pokemon-card.com/assets/images/card_images/large/S7D/039705_P_EAMUDO.jpg"
        },
        {
            "id": "S7D-037",
            "number": "037/067",
            "name": "クレッフィ",
            "rarity": "C",
            "imageUrl": "https://www.pokemon-card.com/assets/images/card_images/large/S7D/039706_P_KUREFFI.jpg"
        },
        {
            "id": "S7D-038",
            "number": "038/067",
            "name": "ゾウドウ",
            "rarity": "C",
            "imageUrl": "https://www.pokemon-card.com/assets/images/card_images/large/S7D/039707_P_ZOUDOU.jpg"
        },
        {
            "id": "S7D-039",
            "number": "039/067",
            "name": "ダイオウドウ",
            "rarity": "U",
            "imageUrl": "https://www.pokemon-card.com/assets/images/card_images/large/S7D/039708_P_DAIOUDOU.jpg"
        },
        {
            "id": "S7D-040",
            "number": "040/067",
            "name": "チルタリス",
            "rarity": "U",
            "imageUrl": "https://www.pokemon-card.com/assets/images/card_images/large/S7D/039709_P_CHIRUTARISU.jpg"
        },
        {
            "id": "S7D-041",
            "number": "041/067",
            "name": "ディアルガ",
            "rarity": "R",
            "imageUrl": "https://www.pokemon-card.com/assets/images/card_images/large/S7D/039710_P_DEIARUGA.jpg"
        },
        {
            "id": "S7D-042",
            "number": "042/067",
            "name": "モノズ",
            "rarity": "C",
            "imageUrl": "https://www.pokemon-card.com/assets/images/card_images/large/S7D/039711_P_MONOZU.jpg"
        },
        {
            "id": "S7D-043",
            "number": "043/067",
            "name": "ジヘッド",
            "rarity": "C",
            "imageUrl": "https://www.pokemon-card.com/assets/images/card_images/large/S7D/039712_P_JIHEDDO.jpg"
        },
        {
            "id": "S7D-044",
            "number": "044/067",
            "name": "サザンドラ",
            "rarity": "R",
            "imageUrl": "https://www.pokemon-card.com/assets/images/card_images/large/S7D/039713_P_SAZANDORA.jpg"
        },
        {
            "id": "S7D-045",
            "number": "045/067",
            "name": "キュレム",
            "rarity": "R",
            "imageUrl": "https://www.pokemon-card.com/assets/images/card_images/large/S7D/039714_P_KYUREMU.jpg"
        },
        {
            "id": "S7D-046",
            "number": "046/067",
            "name": "オンバーンV",
            "rarity": "RR",
            "imageUrl": "https://www.pokemon-card.com/assets/images/card_images/large/S7D/039715_P_ONBANV.jpg"
        },
        {
            "id": "S7D-047",
            "number": "047/067",
            "name": "ジジーロン",
            "rarity": "U",
            "imageUrl": "https://www.pokemon-card.com/assets/images/card_images/large/S7D/039716_P_JIJIRON.jpg"
        },
        {
            "id": "S7D-048",
            "number": "048/067",
            "name": "ジュラルドンV",
            "rarity": "RR",
            "imageUrl": "https://www.pokemon-card.com/assets/images/card_images/large/S7D/039717_P_JURARUDONV.jpg"
        },
        {
            "id": "S7D-049",
            "number": "049/067",
            "name": "ジュラルドンVMAX",
            "rarity": "-",
            "imageUrl": "https://www.pokemon-card.com/assets/images/card_images/large/S7D/039718_P_JURARUDONVMAX.jpg"
        },
        {
            "id": "S7D-050",
            "number": "050/067",
            "name": "ナマケロ",
            "rarity": "C",
            "imageUrl": "https://www.pokemon-card.com/assets/images/card_images/large/S7D/039719_P_NAMAKERO.jpg"
        },
        {
            "id": "S7D-051",
            "number": "051/067",
            "name": "ヤルキモノ",
            "rarity": "C",
            "imageUrl": "https://www.pokemon-card.com/assets/images/card_images/large/S7D/039720_P_YARUKIMONO.jpg"
        },
        {
            "id": "S7D-052",
            "number": "052/067",
            "name": "ケッキング",
            "rarity": "R",
            "imageUrl": "https://www.pokemon-card.com/assets/images/card_images/large/S7D/039721_P_KEKKINGU.jpg"
        },
        {
            "id": "S7D-053",
            "number": "053/067",
            "name": "チルット",
            "rarity": "C",
            "imageUrl": "https://www.pokemon-card.com/assets/images/card_images/large/S7D/039722_P_CHIRUTTO.jpg"
        },
        {
            "id": "S7D-054",
            "number": "054/067",
            "name": "ウールー",
            "rarity": "C",
            "imageUrl": "https://www.pokemon-card.com/assets/images/card_images/large/S7D/039723_P_URU.jpg"
        },
        {
            "id": "S7D-055",
            "number": "055/067",
            "name": "バイウールー",
            "rarity": "C",
            "imageUrl": "https://www.pokemon-card.com/assets/images/card_images/large/S7D/039724_P_BAIURU.jpg"
        },
        {
            "id": "S7D-056",
            "number": "056/067",
            "name": "あなぬけのヒモ",
            "rarity": "U",
            "imageUrl": "https://www.pokemon-card.com/assets/images/card_images/large/S7D/039725_T_ANANUKENOHIMO.jpg"
        },
        {
            "id": "S7D-057",
            "number": "057/067",
            "name": "しんかのおこう",
            "rarity": "U",
            "imageUrl": "https://www.pokemon-card.com/assets/images/card_images/large/S7D/039726_T_SHINKANOOKOU.jpg"
        },
        {
            "id": "S7D-058",
            "number": "058/067",
            "name": "すりかえカップ",
            "rarity": "U",
            "imageUrl": "https://www.pokemon-card.com/assets/images/card_images/large/S7D/039727_T_SURIKAEKAPPU.jpg"
        },
        {
            "id": "S7D-059",
            "number": "059/067",
            "name": "レスキューキャリー",
            "rarity": "U",
            "imageUrl": "https://www.pokemon-card.com/assets/images/card_images/large/S7D/039728_T_RESUKYUKYARI.jpg"
        },
        {
            "id": "S7D-060",
            "number": "060/067",
            "name": "穴掘りグローブ",
            "rarity": "U",
            "imageUrl": "https://www.pokemon-card.com/assets/images/card_images/large/S7D/039729_T_ANAHORIGUROBU.jpg"
        },
        {
            "id": "S7D-061",
            "number": "061/067",
            "name": "いちげきの巻物 牙竜の巻",
            "rarity": "U",
            "imageUrl": "https://www.pokemon-card.com/assets/images/card_images/large/S7D/039730_T_ICHIGEKINOMAKIMONOKIBARYUUNOKAN.jpg"
        },
        {
            "id": "S7D-062",
            "number": "062/067",
            "name": "フルフェイスガード",
            "rarity": "U",
            "imageUrl": "https://www.pokemon-card.com/assets/images/card_images/large/S7D/039731_T_FURUFEISUGADO.jpg"
        },
        {
            "id": "S7D-063",
            "number": "063/067",
            "name": "キバナ",
            "rarity": "U",
            "imageUrl": "https://www.pokemon-card.com/assets/images/card_images/large/S7D/039732_T_KIBANA.jpg"
        },
        {
            "id": "S7D-064",
            "number": "064/067",
            "name": "スクールガール",
            "rarity": "C",
            "imageUrl": "https://www.pokemon-card.com/assets/images/card_images/large/S7D/039733_T_SUKURUGARU.jpg"
        },
        {
            "id": "S7D-065",
            "number": "065/067",
            "name": "モノマネむすめ",
            "rarity": "C",
            "imageUrl": "https://www.pokemon-card.com/assets/images/card_images/large/S7D/039734_T_MONOMANEMUSUME.jpg"
        },
        {
            "id": "S7D-066",
            "number": "066/067",
            "name": "結晶の洞窟",
            "rarity": "U",
            "imageUrl": "https://www.pokemon-card.com/assets/images/card_images/large/S7D/039735_T_KESSHOUNODOUKUTSU.jpg"
        },
        {
            "id": "S7D-067",
            "number": "067/067",
            "name": "ツインエネルギー",
            "rarity": "U",
            "imageUrl": "https://www.pokemon-card.com/assets/images/card_images/large/S7D/039736_E_TSUINENERUGI.jpg"
        },
        {
            "id": "S7D-068",
            "number": "068/067",
            "name": "スイクンV",
            "rarity": "SR",
            "imageUrl": "https://www.pokemon-card.com/assets/images/card_images/large/S7D/039925_P_SUIKUNV.jpg"
        },
        {
            "id": "S7D-069",
            "number": "069/067",
            "name": "ゴルーグV",
            "rarity": "SR",
            "imageUrl": "https://www.pokemon-card.com/assets/images/card_images/large/S7D/039926_P_GORUGUV.jpg"
        },
        {
            "id": "S7D-070",
            "number": "070/067",
            "name": "ゴルーグV",
            "rarity": "SR",
            "imageUrl": "https://www.pokemon-card.com/assets/images/card_images/large/S7D/039927_P_GORUGUV.jpg"
        },
        {
            "id": "S7D-071",
            "number": "071/067",
            "name": "ルガルガンV",
            "rarity": "SR",
            "imageUrl": "https://www.pokemon-card.com/assets/images/card_images/large/S7D/039928_P_RUGARUGANV.jpg"
        },
        {
            "id": "S7D-072",
            "number": "072/067",
            "name": "ダストダスV",
            "rarity": "SR",
            "imageUrl": "https://www.pokemon-card.com/assets/images/card_images/large/S7D/039929_P_DASUTODASUV.jpg"
        },
        {
            "id": "S7D-073",
            "number": "073/067",
            "name": "オンバーンV",
            "rarity": "SR",
            "imageUrl": "https://www.pokemon-card.com/assets/images/card_images/large/S7D/039930_P_ONBANV.jpg"
        },
        {
            "id": "S7D-074",
            "number": "074/067",
            "name": "オンバーンV",
            "rarity": "SR",
            "imageUrl": "https://www.pokemon-card.com/assets/images/card_images/large/S7D/039931_P_ONBANV.jpg"
        },
        {
            "id": "S7D-075",
            "number": "075/067",
            "name": "ジュラルドンV",
            "rarity": "SR",
            "imageUrl": "https://www.pokemon-card.com/assets/images/card_images/large/S7D/039932_P_JURARUDONV.jpg"
        },
        {
            "id": "S7D-076",
            "number": "076/067",
            "name": "ジュラルドンV",
            "rarity": "SR",
            "imageUrl": "https://www.pokemon-card.com/assets/images/card_images/large/S7D/039933_P_JURARUDONV.jpg"
        },
        {
            "id": "S7D-077",
            "number": "077/067",
            "name": "キバナ",
            "rarity": "SR",
            "imageUrl": "https://www.pokemon-card.com/assets/images/card_images/large/S7D/039934_T_KIBANA.jpg"
        },
        {
            "id": "S7D-078",
            "number": "078/067",
            "name": "スクールガール",
            "rarity": "SR",
            "imageUrl": "https://www.pokemon-card.com/assets/images/card_images/large/S7D/039935_T_SUKURUGARU.jpg"
        },
        {
            "id": "S7D-079",
            "number": "079/067",
            "name": "モノマネむすめ",
            "rarity": "SR",
            "imageUrl": "https://www.pokemon-card.com/assets/images/card_images/large/S7D/039936_T_MONOMANEMUSUME.jpg"
        }
    ]
}